hyperlambda/__init__.py
hyperlambda/client.py
hyperlambda/exceptions.py
hyperlambda/helper.py
hyperlambda/main.py
hyperlambda/settings.py
hyperlambda/data/__init__.py
hyperlambda/data/boot.sh
hyperlambda/data/config_sample.ini
hyperlambda-0.0.2.dist-info/DESCRIPTION.rst
hyperlambda-0.0.2.dist-info/METADATA
hyperlambda-0.0.2.dist-info/RECORD
hyperlambda-0.0.2.dist-info/WHEEL
hyperlambda-0.0.2.dist-info/entry_points.txt
hyperlambda-0.0.2.dist-info/metadata.json
hyperlambda-0.0.2.dist-info/top_level.txt
